forceweaver_mcp_server/__init__.py
forceweaver_mcp_server/__main__.py
forceweaver_mcp_server/exceptions.py
forceweaver_mcp_server/server.py
forceweaver_mcp_server-1.1.0.dist-info/licenses/LICENSE
forceweaver_mcp_server-1.1.0.dist-info/METADATA
forceweaver_mcp_server-1.1.0.dist-info/WHEEL
forceweaver_mcp_server-1.1.0.dist-info/entry_points.txt
forceweaver_mcp_server-1.1.0.dist-info/top_level.txt
forceweaver_mcp_server-1.1.0.dist-info/RECORD
