Metadata-Version: 2.4
Name: forceweaver-mcp-server
Version: 1.1.0
Summary: Professional Salesforce Revenue Cloud health checking for AI agents
Author-email: ForceWeaver Team <support@forceweaver.com>
License: MIT
Project-URL: Homepage, https://mcp.forceweaver.com
Project-URL: Documentation, https://github.com/forceweaver/forceweaver-mcp-server
Project-URL: Repository, https://github.com/forceweaver/forceweaver-mcp-server.git
Project-URL: Bug Tracker, https://github.com/forceweaver/forceweaver-mcp-server/issues
Project-URL: Changelog, https://github.com/forceweaver/forceweaver-mcp-server/blob/main/CHANGELOG.md
Keywords: salesforce,mcp,ai,health-check,revenue-cloud,model-context-protocol
Classifier: Development Status :: 5 - Production/Stable
Classifier: Intended Audience :: Developers
Classifier: License :: OSI Approved :: MIT License
Classifier: Operating System :: OS Independent
Classifier: Programming Language :: Python :: 3
Classifier: Programming Language :: Python :: 3.10
Classifier: Programming Language :: Python :: 3.11
Classifier: Programming Language :: Python :: 3.12
Classifier: Topic :: Software Development :: Libraries :: Python Modules
Classifier: Topic :: Internet :: WWW/HTTP :: HTTP Servers
Classifier: Topic :: Communications
Requires-Python: >=3.10
License-File: LICENSE
Requires-Dist: mcp>=1.12.0
Requires-Dist: aiohttp>=3.8.0
Requires-Dist: requests>=2.28.0
Requires-Dist: certifi>=2022.0.0
Provides-Extra: dev
Requires-Dist: pytest>=7.0.0; extra == "dev"
Requires-Dist: pytest-asyncio>=0.21.0; extra == "dev"
Requires-Dist: pytest-cov>=4.0.0; extra == "dev"
Requires-Dist: aioresponses>=0.7.4; extra == "dev"
Requires-Dist: black>=23.0.0; extra == "dev"
Requires-Dist: flake8>=6.0.0; extra == "dev"
Requires-Dist: mypy>=1.0.0; extra == "dev"
Requires-Dist: isort>=5.12.0; extra == "dev"
Dynamic: license-file
